<?xml version="1.0" encoding="utf-8" ?><dwsync><file name=".DS_Store" server="72.32.76.242" local="3515659510" remote="3544623180" Dst="-1" /><file name="jquery-2.1.1.js" server="72.32.76.242" local="3499320220" remote="3544623180" Dst="-1" /><file name="bootstrap.js" server="72.32.76.242" local="3544536707" remote="3544623180" Dst="-1" /><file name="modernizr.js" server="72.32.76.242" local="3499320317" remote="3544623180" Dst="-1" /><file name="main.js" server="72.32.76.242" local="3515659082" remote="3544623180" Dst="-1" /><file name="jquery.responsivetext.js" server="72.32.76.242//Web_Sites/Pinpoint_Merch/" local="3486564252" remote="3544984080" Dst="-1" /><file name="flowtype.js" server="72.32.76.242//Web_Sites/Pinpoint_Merch/" local="3491916992" remote="3544984920" Dst="-1" /><file name="main.js" server="72.32.76.242//Web_Sites/Pinpoint_Merch/" local="3546446289" remote="3546446280" Dst="-1" /></dwsync>